mad_metric/__init__.py
mad_metric/__main__.py
mad_metric/compute_mad.py
mad_metric/embedding_models.py
mad_metric-0.0.6.dist-info/licenses/LICENSE
mad_metric-0.0.6.dist-info/METADATA
mad_metric-0.0.6.dist-info/WHEEL
mad_metric-0.0.6.dist-info/entry_points.txt
mad_metric-0.0.6.dist-info/top_level.txt
mad_metric-0.0.6.dist-info/RECORD
