Metadata-Version: 2.4
Name: mad_metric
Version: 0.0.6
Summary: A metric for acoustic music evaluation based on MAUVE and MERT
Author-email: Yichen Huang <wh4@andrew.cmu.edu>
Project-URL: Homepage, https://github.com/i-need-sleep/mad
Project-URL: Issues, https://github.com/i-need-sleep/mad/issues
Classifier: Programming Language :: Python :: 3
Classifier: Operating System :: OS Independent
Classifier: License :: OSI Approved :: MIT License
Requires-Python: >=3.8
License-File: LICENSE
Requires-Dist: librosa>=0.10.0
Requires-Dist: mauve_text>=0.4.0
Requires-Dist: numpy>=1.23.0
Requires-Dist: pandas>=2.0.0
Requires-Dist: torch>=2.4.1
Requires-Dist: tqdm>=4.66.0
Requires-Dist: transformers>=4.31.0
Dynamic: license-file
